simple_kanban_gui/__init__.py
simple_kanban_gui/about.py
simple_kanban_gui/desktop.py
simple_kanban_gui/manager.py
simple_kanban_gui/program.py
simple_kanban_gui/icons/logo.png
simple_kanban_gui/modules/__init__.py
simple_kanban_gui/modules/configure.py
simple_kanban_gui/modules/wabout.py
simple_kanban_gui-0.1.9.dist-info/licenses/LICENSE
simple_kanban_gui-0.1.9.dist-info/METADATA
simple_kanban_gui-0.1.9.dist-info/WHEEL
simple_kanban_gui-0.1.9.dist-info/entry_points.txt
simple_kanban_gui-0.1.9.dist-info/top_level.txt
simple_kanban_gui-0.1.9.dist-info/RECORD
