Metadata-Version: 2.4
Name: simple_kanban_gui
Version: 0.1.9
Summary: A simple kanban graphic user interface
Author-email: Fernando Pujaico Rivera <fernando.pujaico.rivera@gmail.com>
Maintainer-email: Fernando Pujaico Rivera <fernando.pujaico.rivera@gmail.com>
License-Expression: GPL-3.0-only WITH Classpath-exception-2.0 OR BSD-3-Clause
Project-URL: Bug Reports, https://github.com/trucomanx/SimpleKanbanGUI/issues
Project-URL: Funding, https://trucomanx.github.io/en/funding.html
Project-URL: Documentation, https://github.com/trucomanx/SimpleKanbanGUI/tree/main/doc
Project-URL: Source, https://github.com/trucomanx/SimpleKanbanGUI
Keywords: kanban,productivity,task,to-do
Classifier: Programming Language :: Python :: 3
Classifier: Operating System :: OS Independent
Requires-Python: >=3.8
License-File: LICENSE
Requires-Dist: PyQt5
Dynamic: license-file
